libplist/__init__.py
libplist-0.1.dist-info/LICENSE
libplist-0.1.dist-info/WHEEL
libplist-0.1.dist-info/METADATA
libplist-0.1.dist-info/RECORD
