Metadata-Version: 2.1
Name: libplist
Version: 0.1
Summary: Python bindings to libplist
Home-page: https://github.com/libimobiledevice/python-libplist
License: UNKNOWN
Author: Rick Mark
Author-email: rickmark@guardianapp.com
